[{"Availability":"a","Specialization":"a","Id":"DOC125","Patients":0,"Name":"za"},{"Availability":"a","Specialization":"a","Id":"DOC861","Patients":1,"Name":"a"},{"Availability":"s","Specialization":"a","Id":"DOC125","Patients":0,"Name":"a"},{"Availability":"a","Specialization":"a","Id":"DOC126","Patients":0,"Name":"a"},{"Availability":"morning","Specialization":"skin","Id":"DOC110","Patients":4,"Name":"Ritesh"},{"Availability":"yes","Specialization":"ortho","Id":"DOC482","Patients":0,"Name":"Ritesh"},{"Availability":"yes","Specialization":"ortho","Id":"DOC690","Patients":0,"Name":"duraj"},{"Availability":"Yes","Specialization":"Ortho","Id":"DOC790","Patients":0,"Name":"Ritesh"},{"Availability":"yes","Specialization":"ortho","Id":"DOC449","Patients":0,"Name":"ritesh"},{"Availability":null,"Specialization":"ortho","Id":"DOC792","Patients":0,"Name":"Ritesh"},{"Availability":"Yes","Specialization":"Ortho","Id":"DOC514","Patients":0,"Name":"Ritesh"},{"Availability":"am","Specialization":"Skin","Id":"DOC577","Patients":0,"Name":"Ritesh"}]